wmgraph/__init__.py
wmgraph/__main__.py
wmgraph/api/__init__.py
wmgraph/api/auditlogs.py
wmgraph/api/base.py
wmgraph/api/cache.py
wmgraph/api/deleted.py
wmgraph/api/deltaiterator.py
wmgraph/api/drive.py
wmgraph/api/exceptions.py
wmgraph/api/group.py
wmgraph/api/site.py
wmgraph/api/tokencache.py
wmgraph/api/user.py
wmgraph/api/usercontact.py
wmgraph/utils/__init__.py
wmgraph-0.7.1.dist-info/LICENSE
wmgraph-0.7.1.dist-info/METADATA
wmgraph-0.7.1.dist-info/WHEEL
wmgraph-0.7.1.dist-info/top_level.txt
wmgraph-0.7.1.dist-info/RECORD
