Metadata-Version: 2.1
Name: wmgraph
Version: 0.7.1
Summary: Microsoft Graph convenience library
Home-page: https://github.com/patrickatamaniuk/wmgraph
Author: Patrick Atamaniuk, wibas GmbH
Author-email: patrick.atamaniuk@wibas.com
License: MIT License
Keywords: Information Security,Microsoft,GraphAPI,graph api
Platform: UNKNOWN
Classifier: Development Status :: 3 - Alpha
Classifier: Intended Audience :: Developers
Classifier: Intended Audience :: Information Technology
Classifier: Intended Audience :: Telecommunications Industry
Classifier: Topic :: Office/Business
Classifier: Topic :: System :: Systems Administration :: Authentication/Directory
Classifier: Operating System :: OS Independent
Classifier: License :: OSI Approved :: MIT License
Classifier: Programming Language :: Python :: 3 :: Only
Classifier: Programming Language :: Python :: 3
Requires-Dist: requests (<3,>=2)
Requires-Dist: msal (<2,>=0)
Requires-Dist: quickxorhash
